iautil/.gitignore
iautil/__init__.py
iautil/__init__.py-0
iautil/citations.py
iautil/citations.py-0
iautil/doc.py-0
iautil/log.py
iautil/log.py-0
iautil/oops.py
iautil/oops.py-0
iautil/predicates.py
iautil/predicates.py-0
iautil/version.py
iautil/version.py-0
iautil-0.0.18.dist-info/LICENSE
iautil-0.0.18.dist-info/METADATA
iautil-0.0.18.dist-info/WHEEL
iautil-0.0.18.dist-info/top_level.txt
iautil-0.0.18.dist-info/RECORD
